cmm.cpython-312-aarch64-linux-gnu.so
cmm.pyi
cmm_16bit-0.1.6.dist-info/METADATA
cmm_16bit-0.1.6.dist-info/WHEEL
cmm_16bit-0.1.6.dist-info/top_level.txt
cmm_16bit-0.1.6.dist-info/RECORD
cmm_16bit-0.1.6.dist-info/licenses/LICENSE
